remote_sge-0.2.8.data/data/bin/remote_sge_job_wrapper.sh
remote_sge-0.2.8.data/data/etc/remote_sge/client_config.ini
remote_sge-0.2.8.data/data/etc/remote_sge/config.ini
remote_sge-0.2.8.data/data/etc/remote_sge/gunicorn.service
remote_sge-0.2.8.data/data/etc/remote_sge/gunicorn_config.py
remote_sge-0.2.8.data/data/etc/remote_sge/gunicorn_init.d.sh
remote_sge-0.2.8.data/data/etc/remote_sge/gunicorn_upstart.conf
remote_sge-0.2.8.data/data/etc/remote_sge/logging.conf
remote_sge-0.2.8.data/data/etc/remote_sge/nginx.conf
remote_sge-0.2.8.data/data/etc/remote_sge/openssl-ca.ini
remote_sge-0.2.8.data/data/etc/remote_sge/openssl-client.ini
remote_sge-0.2.8.data/data/etc/remote_sge/openssl-server.ini
remote_sge-0.2.8.data/data/etc/remote_sge/ssl_config.ini
remote_sge-0.2.8.data/data/etc/remote_sge/supervisord.conf
remote_sge-0.2.8.data/scripts/remote_sge_job_wrapper.sh
remote_sge-0.2.8.dist-info/METADATA
remote_sge-0.2.8.dist-info/RECORD
remote_sge-0.2.8.dist-info/WHEEL
remote_sge-0.2.8.dist-info/entry_points.txt
remote_sge-0.2.8.dist-info/top_level.txt
sge/__init__.py
sge/config_base.py
sge/control.py
sge/shell.py
sge/status.py
sge/submit.py
sge/io/config.py
sge/util/__init__.py
sge/util/arg_parser.py
sge/util/cmd_opt_descriptor.py
sge/util/entrypoint.py
sge/util/serializers.py
sge/util/xpath_attr_desciptor.py
sge_client/__init__.py
sge_client/client_config.py
sge_client/shuttle.py
sge_client/io/__init__.py
sge_client/io/database.py
sge_client/io/jobarchive.py
sge_client/io/qstat.py
sge_client/util/__init__.py
sge_client/util/install_cert.py
sge_client/util/install_client.py
sge_client/util/request_certificate.py
sge_client/util/string_to_int_list.py
sge_server/__init__.py
sge_server/server_config.py
sge_server/views.py
sge_server/util/__init__.py
sge_server/util/check_server.py
sge_server/util/install_server.py
sge_server/util/sign_cert.py
