Metadata-Version: 2.1
Name: remote-sge
Version: 0.2.8
Summary: Utilities for remote submission and collection of GridEngine jobs.
Home-page: https://github.com/tylergannon/remote_sge
Author: Tyler Gannon
Author-email: tyler.gannon@interxinc.com
License: Apache2
Platform: UNKNOWN
Classifier: Development Status :: 4 - Beta
Classifier: Intended Audience :: System Administrators
Classifier: License :: OSI Approved :: Apache Software License
Classifier: Programming Language :: Python :: 3
Provides-Extra: testing
Requires-Dist: requests (==2.18.4)
Requires-Dist: filelock (>=2.0)
Requires-Dist: falcon (>=1.4.0rc2)
Requires-Dist: gunicorn (>=19.7.1)
Requires-Dist: configobj (>=5.0.6)
Provides-Extra: testing
Requires-Dist: pytest (==3.6.0); extra == 'testing'
Requires-Dist: pytest-mock; extra == 'testing'
Requires-Dist: pytest-bdd; extra == 'testing'
Requires-Dist: pytest-timeout; extra == 'testing'
Requires-Dist: twine; extra == 'testing'
Requires-Dist: vcrpy; extra == 'testing'
Requires-Dist: pylint; extra == 'testing'
Requires-Dist: setuptools; extra == 'testing'
Requires-Dist: wheel; extra == 'testing'
Requires-Dist: requests-unixsocket; extra == 'testing'
